{"sync_to":"2013-06-27","data":{"2013-06-27":{"Symbol":"WTFCW","Date":"2013-06-27","Open":"18.15","High":"18.15","Low":"18.15","Close":"18.15","Volume":"100","Adj_Close":"18.15"},"2013-06-26":{"Symbol":"WTFCW","Date":"2013-06-26","Open":"17.80","High":"17.80","Low":"17.80","Close":"17.80","Volume":"000","Adj_Close":"17.80"},"2013-06-25":{"Symbol":"WTFCW","Date":"2013-06-25","Open":"17.80","High":"17.80","Low":"17.80","Close":"17.80","Volume":"100","Adj_Close":"17.80"},"2013-06-24":{"Symbol":"WTFCW","Date":"2013-06-24","Open":"17.35","High":"17.35","Low":"17.35","Close":"17.35","Volume":"100","Adj_Close":"17.35"},"2013-06-21":{"Symbol":"WTFCW","Date":"2013-06-21","Open":"17.30","High":"17.55","Low":"17.30","Close":"17.55","Volume":"300","Adj_Close":"17.55"},"2013-06-20":{"Symbol":"WTFCW","Date":"2013-06-20","Open":"16.90","High":"17.04","Low":"16.90","Close":"17.04","Volume":"200","Adj_Close":"17.04"},"2013-06-19":{"Symbol":"WTFCW","Date":"2013-06-19","Open":"16.50","High":"16.50","Low":"16.50","Close":"16.50","Volume":"000","Adj_Close":"16.50"},"2013-06-18":{"Symbol":"WTFCW","Date":"2013-06-18","Open":"16.50","High":"16.50","Low":"16.50","Close":"16.50","Volume":"100","Adj_Close":"16.50"},"2013-06-17":{"Symbol":"WTFCW","Date":"2013-06-17","Open":"16.54","High":"16.54","Low":"16.54","Close":"16.54","Volume":"100","Adj_Close":"16.54"},"2013-06-14":{"Symbol":"WTFCW","Date":"2013-06-14","Open":"16.45","High":"16.45","Low":"16.45","Close":"16.45","Volume":"100","Adj_Close":"16.45"},"2013-06-13":{"Symbol":"WTFCW","Date":"2013-06-13","Open":"16.90","High":"16.90","Low":"16.90","Close":"16.90","Volume":"100","Adj_Close":"16.90"},"2013-06-12":{"Symbol":"WTFCW","Date":"2013-06-12","Open":"16.50","High":"16.50","Low":"16.50","Close":"16.50","Volume":"100","Adj_Close":"16.50"},"2013-06-11":{"Symbol":"WTFCW","Date":"2013-06-11","Open":"16.80","High":"16.80","Low":"16.80","Close":"16.80","Volume":"000","Adj_Close":"16.80"},"2013-06-10":{"Symbol":"WTFCW","Date":"2013-06-10","Open":"16.80","High":"16.80","Low":"16.80","Close":"16.80","Volume":"000","Adj_Close":"16.80"},"2013-06-07":{"Symbol":"WTFCW","Date":"2013-06-07","Open":"16.80","High":"16.80","Low":"16.80","Close":"16.80","Volume":"000","Adj_Close":"16.80"},"2013-06-06":{"Symbol":"WTFCW","Date":"2013-06-06","Open":"16.80","High":"16.80","Low":"16.80","Close":"16.80","Volume":"100","Adj_Close":"16.80"},"2013-06-05":{"Symbol":"WTFCW","Date":"2013-06-05","Open":"16.34","High":"17.00","Low":"16.34","Close":"17.00","Volume":"400","Adj_Close":"17.00"},"2013-06-04":{"Symbol":"WTFCW","Date":"2013-06-04","Open":"17.70","High":"17.70","Low":"17.70","Close":"17.70","Volume":"000","Adj_Close":"17.70"},"2013-06-03":{"Symbol":"WTFCW","Date":"2013-06-03","Open":"17.70","High":"17.70","Low":"17.70","Close":"17.70","Volume":"000","Adj_Close":"17.70"},"2013-05-31":{"Symbol":"WTFCW","Date":"2013-05-31","Open":"17.70","High":"17.70","Low":"17.70","Close":"17.70","Volume":"000","Adj_Close":"17.70"},"2013-05-30":{"Symbol":"WTFCW","Date":"2013-05-30","Open":"17.70","High":"17.70","Low":"17.70","Close":"17.70","Volume":"000","Adj_Close":"17.70"},"2013-05-29":{"Symbol":"WTFCW","Date":"2013-05-29","Open":"17.70","High":"17.70","Low":"17.70","Close":"17.70","Volume":"000","Adj_Close":"17.70"},"2013-05-28":{"Symbol":"WTFCW","Date":"2013-05-28","Open":"17.70","High":"17.70","Low":"17.70","Close":"17.70","Volume":"100","Adj_Close":"17.70"}}}