{"sync_to":"2013-06-27","data":{"2013-06-27":{"Symbol":"GYRO","Date":"2013-06-27","Open":"71.82","High":"71.96","Low":"70.65","Close":"71.50","Volume":"13500","Adj_Close":"19.76"},"2013-06-26":{"Symbol":"GYRO","Date":"2013-06-26","Open":"71.75","High":"71.75","Low":"70.20","Close":"70.82","Volume":"12800","Adj_Close":"19.57"},"2013-06-25":{"Symbol":"GYRO","Date":"2013-06-25","Open":"71.31","High":"71.45","Low":"70.11","Close":"71.45","Volume":"5000","Adj_Close":"19.74"},"2013-06-24":{"Symbol":"GYRO","Date":"2013-06-24","Open":"71.43","High":"71.78","Low":"70.59","Close":"70.60","Volume":"10100","Adj_Close":"19.51"},"2013-06-21":{"Symbol":"GYRO","Date":"2013-06-21","Open":"71.83","High":"71.89","Low":"70.42","Close":"71.89","Volume":"10100","Adj_Close":"19.86"},"2013-06-20":{"Symbol":"GYRO","Date":"2013-06-20","Open":"72.00","High":"72.00","Low":"70.10","Close":"71.51","Volume":"6300","Adj_Close":"19.76"},"2013-06-19":{"Symbol":"GYRO","Date":"2013-06-19","Open":"72.01","High":"72.37","Low":"71.50","Close":"71.77","Volume":"3000","Adj_Close":"19.83"},"2013-06-18":{"Symbol":"GYRO","Date":"2013-06-18","Open":"71.46","High":"72.49","Low":"71.46","Close":"72.27","Volume":"3800","Adj_Close":"19.97"},"2013-06-17":{"Symbol":"GYRO","Date":"2013-06-17","Open":"72.80","High":"72.80","Low":"71.74","Close":"72.37","Volume":"8800","Adj_Close":"20.00"},"2013-06-14":{"Symbol":"GYRO","Date":"2013-06-14","Open":"72.52","High":"72.53","Low":"69.01","Close":"72.37","Volume":"6400","Adj_Close":"20.00"},"2013-06-13":{"Symbol":"GYRO","Date":"2013-06-13","Open":"72.63","High":"72.79","Low":"70.50","Close":"72.70","Volume":"8800","Adj_Close":"20.09"},"2013-06-12":{"Symbol":"GYRO","Date":"2013-06-12","Open":"72.50","High":"72.88","Low":"72.50","Close":"72.54","Volume":"2400","Adj_Close":"20.04"},"2013-06-11":{"Symbol":"GYRO","Date":"2013-06-11","Open":"72.30","High":"72.98","Low":"71.88","Close":"72.63","Volume":"5700","Adj_Close":"20.07"},"2013-06-10":{"Symbol":"GYRO","Date":"2013-06-10","Open":"72.89","High":"72.97","Low":"71.71","Close":"72.80","Volume":"4100","Adj_Close":"20.12"},"2013-06-07":{"Symbol":"GYRO","Date":"2013-06-07","Open":"72.91","High":"73.06","Low":"72.82","Close":"73.04","Volume":"4200","Adj_Close":"20.18"},"2013-06-06":{"Symbol":"GYRO","Date":"2013-06-06","Open":"72.84","High":"73.18","Low":"70.76","Close":"73.15","Volume":"6000","Adj_Close":"20.21"},"2013-06-05":{"Symbol":"GYRO","Date":"2013-06-05","Open":"73.00","High":"73.19","Low":"72.03","Close":"72.75","Volume":"5800","Adj_Close":"20.10"},"2013-06-04":{"Symbol":"GYRO","Date":"2013-06-04","Open":"73.20","High":"73.42","Low":"72.52","Close":"73.01","Volume":"3000","Adj_Close":"20.17"},"2013-06-03":{"Symbol":"GYRO","Date":"2013-06-03","Open":"71.89","High":"73.93","Low":"71.89","Close":"73.40","Volume":"8700","Adj_Close":"20.28"},"2013-05-31":{"Symbol":"GYRO","Date":"2013-05-31","Open":"72.49","High":"73.15","Low":"71.70","Close":"73.15","Volume":"9500","Adj_Close":"20.21"},"2013-05-30":{"Symbol":"GYRO","Date":"2013-05-30","Open":"72.96","High":"73.13","Low":"72.55","Close":"73.00","Volume":"5500","Adj_Close":"20.17"},"2013-05-29":{"Symbol":"GYRO","Date":"2013-05-29","Open":"73.22","High":"73.22","Low":"73.01","Close":"73.03","Volume":"3200","Adj_Close":"20.18"},"2013-05-28":{"Symbol":"GYRO","Date":"2013-05-28","Open":"73.50","High":"73.58","Low":"72.61","Close":"73.46","Volume":"1600","Adj_Close":"20.30"}}}